{"cameraMode":{"drawMode":0,"name":"Shaded","section":"Shading Mode"},"sceneLighting":false,"audioPlay":false,"sceneViewState":{"m_AlwaysRefresh":false,"showFog":true,"showSkybox":false,"showFlares":true,"showImageEffects":true,"showParticleSystems":true,"showVisualEffectGraphs":true,"m_FxEnabled":true},"in2DMode":false,"pivot":{"x":-0.6966003179550171,"y":1.1824990510940552,"z":12.837030410766602},"rotation":{"x":-0.4093424379825592,"y":0.016966184601187707,"z":-0.007613719906657934,"w":-0.9121949672698975},"size":2.1982858180999758,"orthographic":false}